{"Zdravo": {"created_at": {"$date": 1489974522434}, "extra_data": {}, "in_response_to": []}, "#samojako": {"created_at": {"$date": 1489974522489}, "extra_data": {}, "in_response_to": [{"text": "Ave Beli", "occurrence": 13}]}, "samo jako": {"created_at": {"$date": 1489975028608}, "extra_data": {}, "in_response_to": [{"text": "#samojako", "occurrence": 1}]}, "Ko je beli?": {"created_at": {"$date": 1489984913288}, "extra_data": {}, "in_response_to": [{"text": "Sve pare ce da budu kod cike", "occurrence": 11}, {"text": "САМО ЈАКО - СИРОТИЊА УЗВРАЋА УДАРАЦ!", "occurrence": 11}]}, "Ave Beli": {"created_at": {"$date": 1489974522464}, "extra_data": {}, "in_response_to": [{"text": "Ćao", "occurrence": 13}, {"text": "U precedničkoj fotelji", "occurrence": 13}]}, "Vreme je za sarmu - Sarmu Probo Nisi": {"created_at": {"$date": 1489974522444}, "extra_data": {}, "in_response_to": [{"text": "Kolko ima sati?", "occurrence": 13}]}, "Ljubi čika": {"created_at": {"$date": 1489974522469}, "extra_data": {}, "in_response_to": [{"text": "Ave Beli", "occurrence": 13}, {"text": "Pozdrav", "occurrence": 13}, {"text": "Zdravo Beli", "occurrence": 11}]}, "De si Beli": {"created_at": {"$date": 1489974522482}, "extra_data": {}, "in_response_to": [{"text": "Samo da ste mi lepi i veseli", "occurrence": 13}]}, "Samo jako, đeco moja, ne dajte da vas malerišu i baronišu!": {"created_at": {"$date": 1489984913338}, "extra_data": {}, "in_response_to": [{"text": "Poruka za decu?", "occurrence": 11}]}, "5 пољупца хоћу ја, нећу 1 нећу 2 ! САМО ЈАКО!!!": {"created_at": {"$date": 1489984913349}, "extra_data": {}, "in_response_to": [{"text": "Poljubac", "occurrence": 11}]}, "Pozdrav": {"created_at": {"$date": 1489974522473}, "extra_data": {}, "in_response_to": [{"text": "Ljubi čika", "occurrence": 13}]}, "ave": {"created_at": {"$date": 1489974534372}, "extra_data": {}, "in_response_to": [{"text": "Ave Beli!", "occurrence": 1}, {"text": "#samojako", "occurrence": 1}]}, "Ha ha ha ha": {"created_at": {"$date": 1489974522446}, "extra_data": {}, "in_response_to": [{"text": "Vreme je za sarmu - Sarmu Probo Nisi", "occurrence": 13}]}, "Gde smo?": {"created_at": {"$date": 1489984913321}, "extra_data": {}, "in_response_to": [{"text": "Sine. šta me snimaš dok jedem", "occurrence": 11}]}, "#avebeli": {"created_at": {"$date": 1489974522492}, "extra_data": {}, "in_response_to": [{"text": "#samojako", "occurrence": 14}]}, "kolko ima sati": {"created_at": {"$date": 1489974583576}, "extra_data": {}, "in_response_to": [{"text": "#samojako", "occurrence": 1}]}, "U precedničkoj fotelji": {"created_at": {"$date": 1489974522484}, "extra_data": {}, "in_response_to": [{"text": "De si Beli", "occurrence": 13}]}, "Ave Beli!": {"created_at": {"$date": 1489974522447}, "extra_data": {}, "in_response_to": [{"text": "Ha ha ha ha", "occurrence": 13}, {"text": "Gađaju me neke tamo agencije sa 11%, nemo se zezamo. Više verujem Najngegu. Gura čika do pobede! Sirotinja uzvraća udarac!", "occurrence": 11}]}, "1": {"created_at": {"$date": 1489974522512}, "extra_data": {}, "in_response_to": []}, "САМО ЈАКО - СИРОТИЊА УЗВРАЋА УДАРАЦ!": {"created_at": {"$date": 1489984913361}, "extra_data": {}, "in_response_to": [{"text": "kako?", "occurrence": 11}]}, "Samo jako!Samo bez sikiracije": {"created_at": {"$date": 1489974522441}, "extra_data": {}, "in_response_to": [{"text": "Samo bez sikiracije", "occurrence": 13}]}, "kako do pobede?Časno i pošteno do pobede, vreme je da na čelo ove naše lepe Srbije stane osoba mlada,perspektivna, školovana, jer na mladjima svet ostaje, dokle više da gledamo matore keše kao Krkobabiće i njima slične. Napred Beli, Samo Jako, Šabac je uz tebe❤❤❤": {"created_at": {"$date": 1489984913274}, "extra_data": {}, "in_response_to": [{"text": "Najverovatnije ključ pobede i drugog krga drže A P S T I N E N T I: Dakle nikakvo ubeđivanje matoraca, nego apstinenata da izađu i glasaju. Njih ima blizu 45% dakle preko 3miliona.Ako svaki 5. izađe to je 600K glasova za Čiku + mi ostali. Znači možda i ceo milion! E tu je 2. krug siguran. Opšte je poznato od 90. naovamo da se vlast i opozicija kreću između 1,5 i 2 mil glasova (i jedni i drugi) sa naših milion to je između 4-5 miliona. Naš milion + opozicija(Jeremić, Janković i ostali) u 2. krugu daju minimum 500K glasova više nego diktator.. A onda ne može ni sa krađom da nas stigne!", "occurrence": 11}]}, "kako si": {"created_at": {"$date": 1489974550517}, "extra_data": {}, "in_response_to": [{"text": "#samojako", "occurrence": 1}]}, "Samo da ste mi lepi i veseli": {"created_at": {"$date": 1489974522480}, "extra_data": {}, "in_response_to": [{"text": "Ljubi čika", "occurrence": 13}]}, "Koliko posto?": {"created_at": {"$date": 1489984913395}, "extra_data": {}, "in_response_to": [{"text": "АВЕ БЕЛИ ! 5 !", "occurrence": 11}]}, "Kako si?": {"created_at": {"$date": 1489974522437}, "extra_data": {}, "in_response_to": [{"text": "Ljubi čika!", "occurrence": 2}, {"text": "Ljubi čika", "occurrence": 11}]}, "Odoh": {"created_at": {"$date": 1489984913421}, "extra_data": {}, "in_response_to": [{"text": "Do pobede!", "occurrence": 11}]}, "3": {"created_at": {"$date": 1489974522518}, "extra_data": {}, "in_response_to": [{"text": "2", "occurrence": 2}]}, "2": {"created_at": {"$date": 1489974522515}, "extra_data": {}, "in_response_to": [{"text": "1", "occurrence": 2}]}, "avež": {"created_at": {"$date": 1489975025168}, "extra_data": {}, "in_response_to": [{"text": "Ave Beli", "occurrence": 1}]}, "4": {"created_at": {"$date": 1489974522521}, "extra_data": {}, "in_response_to": [{"text": "3", "occurrence": 2}]}, "7": {"created_at": {"$date": 1489974522530}, "extra_data": {}, "in_response_to": [{"text": "6", "occurrence": 2}]}, "pozdrav": {"created_at": {"$date": 1489974559460}, "extra_data": {}, "in_response_to": [{"text": "#samojako", "occurrence": 1}]}, "Ljubi čika!": {"created_at": {"$date": 1489974522435}, "extra_data": {}, "in_response_to": [{"text": "Zdravo", "occurrence": 13}, {"text": "Zdravo Beli!", "occurrence": 2}, {"text": "Cao", "occurrence": 2}, {"text": "Pozdrav", "occurrence": 2}]}, "5": {"created_at": {"$date": 1489974522523}, "extra_data": {}, "in_response_to": [{"text": "4", "occurrence": 2}]}, "Do pobede!": {"created_at": {"$date": 1489984913415}, "extra_data": {}, "in_response_to": [{"text": "Ave Beli!", "occurrence": 11}]}, "АВЕ БЕЛИ ! 5 !": {"created_at": {"$date": 1489984913389}, "extra_data": {}, "in_response_to": [{"text": "Samo napred", "occurrence": 11}]}, "i ja kazem": {"created_at": {"$date": 1489974537984}, "extra_data": {}, "in_response_to": [{"text": "#samojako", "occurrence": 1}]}, "Poljubac": {"created_at": {"$date": 1489984913343}, "extra_data": {}, "in_response_to": [{"text": "Samo jako, đeco moja, ne dajte da vas malerišu i baronišu!", "occurrence": 11}]}, "kako?": {"created_at": {"$date": 1489984913355}, "extra_data": {}, "in_response_to": [{"text": "5 пољупца хоћу ја, нећу 1 нећу 2 ! САМО ЈАКО!!!", "occurrence": 11}]}, "apstinenti?": {"created_at": {"$date": 1489984913264}, "extra_data": {}, "in_response_to": [{"text": "#avebeli", "occurrence": 11}]}, "6": {"created_at": {"$date": 1489974522526}, "extra_data": {}, "in_response_to": [{"text": "5", "occurrence": 2}]}, "Samo Jako!": {"created_at": {"$date": 1489974522438}, "extra_data": {}, "in_response_to": [{"text": "Kako si?", "occurrence": 13}]}, "Beli im napravio spoj farme, parova i cirilice. Ovo je bolje nego da je otisao u studio. Koliko tupsona ce ladno da poveruje bukvalno u sve ovo": {"created_at": {"$date": 1489984913293}, "extra_data": {}, "in_response_to": [{"text": "Ko je beli?", "occurrence": 11}]}, "Sine. šta me snimaš dok jedem": {"created_at": {"$date": 1489984913304}, "extra_data": {}, "in_response_to": [{"text": "Snimanje", "occurrence": 11}, {"text": "Hrana", "occurrence": 11}]}, "ave beli": {"created_at": {"$date": 1489974555110}, "extra_data": {}, "in_response_to": [{"text": "Samo Jako!", "occurrence": 1}, {"text": "Ljubi čika", "occurrence": 1}]}, "9": {"created_at": {"$date": 1489974522536}, "extra_data": {}, "in_response_to": [{"text": "8", "occurrence": 2}]}, "I ja isto": {"created_at": {"$date": 1489974522439}, "extra_data": {}, "in_response_to": [{"text": "Samo Jako!", "occurrence": 13}]}, "Будући преЦедник ГО Младеновац, а и републике Србије. САМО ЈАКО !": {"created_at": {"$date": 1489984913376}, "extra_data": {}, "in_response_to": [{"text": "Ko je beli?", "occurrence": 11}]}, "Cao": {"created_at": {"$date": 1489974522500}, "extra_data": {}, "in_response_to": []}, "opa": {"created_at": {"$date": 1489974527900}, "extra_data": {}, "in_response_to": [{"text": "U precedničkoj fotelji", "occurrence": 1}, {"text": "Vreme je za sarmu - Sarmu Probo Nisi", "occurrence": 1}]}, "Zdravo Beli": {"created_at": {"$date": 1489984913137}, "extra_data": {}, "in_response_to": [{"text": "Ljubi čika!", "occurrence": 11}]}, "ljubi i tebe": {"created_at": {"$date": 1489974960555}, "extra_data": {}, "in_response_to": [{"text": "Ljubi čika", "occurrence": 1}]}, "Gađaju me neke tamo agencije sa 11%, nemo se zezamo. Više verujem Najngegu. Gura čika do pobede! Sirotinja uzvraća udarac!": {"created_at": {"$date": 1489984913401}, "extra_data": {}, "in_response_to": [{"text": "Koliko posto?", "occurrence": 11}]}, "Samo napred": {"created_at": {"$date": 1489984913383}, "extra_data": {}, "in_response_to": [{"text": "Будући преЦедник ГО Младеновац, а и републике Србије. САМО ЈАКО !", "occurrence": 11}]}, "Sve pare ce da budu kod cike": {"created_at": {"$date": 1489984913283}, "extra_data": {}, "in_response_to": [{"text": "gde su pare?", "occurrence": 11}]}, "Kolko ima sati?": {"created_at": {"$date": 1489974522443}, "extra_data": {}, "in_response_to": [{"text": "Samo jako!Samo bez sikiracije", "occurrence": 13}]}, "odoh": {"created_at": {"$date": 1489974566760}, "extra_data": {}, "in_response_to": [{"text": "Ljubi čika!", "occurrence": 1}, {"text": "Samo bez sikiracije", "occurrence": 1}]}, "Zdravo Beli!": {"created_at": {"$date": 1489974522495}, "extra_data": {}, "in_response_to": []}, "Gruvaj beli": {"created_at": {"$date": 1489974544658}, "extra_data": {}, "in_response_to": [{"text": "Samo bez sikiracije", "occurrence": 1}]}, "Љуби чика идите вечерас проведите се, радујте се бољим данима, нек је весеље !": {"created_at": {"$date": 1489984913428}, "extra_data": {}, "in_response_to": [{"text": "Odoh", "occurrence": 10}]}, "Poruka za decu?": {"created_at": {"$date": 1489984913332}, "extra_data": {}, "in_response_to": [{"text": "Mesto zbivanja: Proročište na Belianum vis-u centralni Ilirikum!!! (y)", "occurrence": 11}]}, "de si": {"created_at": {"$date": 1489974525784}, "extra_data": {}, "in_response_to": []}, "gde su pare?": {"created_at": {"$date": 1489984913278}, "extra_data": {}, "in_response_to": [{"text": "kako do pobede?Časno i pošteno do pobede, vreme je da na čelo ove naše lepe Srbije stane osoba mlada,perspektivna, školovana, jer na mladjima svet ostaje, dokle više da gledamo matore keše kao Krkobabiće i njima slične. Napred Beli, Samo Jako, Šabac je uz tebe❤❤❤", "occurrence": 11}]}, "Mesto zbivanja: Proročište na Belianum vis-u centralni Ilirikum!!! (y)": {"created_at": {"$date": 1489984913327}, "extra_data": {}, "in_response_to": [{"text": "Gde smo?", "occurrence": 11}]}, "ćao": {"created_at": {"$date": 1489975022433}, "extra_data": {}, "in_response_to": [{"text": "Ljubi čika", "occurrence": 1}]}, "Snimanje": {"created_at": {"$date": 1489984913299}, "extra_data": {}, "in_response_to": [{"text": "Beli im napravio spoj farme, parova i cirilice. Ovo je bolje nego da je otisao u studio. Koliko tupsona ce ladno da poveruje bukvalno u sve ovo", "occurrence": 11}]}, "cao": {"created_at": {"$date": 1489974563188}, "extra_data": {}, "in_response_to": [{"text": "Ljubi čika", "occurrence": 1}, {"text": "Pozdrav", "occurrence": 1}, {"text": "ave beli", "occurrence": 1}]}, "Ćao": {"created_at": {"$date": 1489974522449}, "extra_data": {}, "in_response_to": [{"text": "Ave Beli!", "occurrence": 13}, {"text": "Ćao", "occurrence": 13}]}, "hahaha": {"created_at": {"$date": 1489974532529}, "extra_data": {}, "in_response_to": [{"text": "Ljubi čika", "occurrence": 1}]}, "Najverovatnije ključ pobede i drugog krga drže A P S T I N E N T I: Dakle nikakvo ubeđivanje matoraca, nego apstinenata da izađu i glasaju. Njih ima blizu 45% dakle preko 3miliona.Ako svaki 5. izađe to je 600K glasova za Čiku + mi ostali. Znači možda i ceo milion! E tu je 2. krug siguran. Opšte je poznato od 90. naovamo da se vlast i opozicija kreću između 1,5 i 2 mil glasova (i jedni i drugi) sa naših milion to je između 4-5 miliona. Naš milion + opozicija(Jeremić, Janković i ostali) u 2. krugu daju minimum 500K glasova više nego diktator.. A onda ne može ni sa krađom da nas stigne!": {"created_at": {"$date": 1489984913268}, "extra_data": {}, "in_response_to": [{"text": "apstinenti?", "occurrence": 11}]}, "Hrana": {"created_at": {"$date": 1489984913309}, "extra_data": {}, "in_response_to": [{"text": "Sine. šta me snimaš dok jedem", "occurrence": 11}]}, "Samo bez sikiracije": {"created_at": {"$date": 1489974522440}, "extra_data": {}, "in_response_to": [{"text": "I ja isto", "occurrence": 13}]}, "8": {"created_at": {"$date": 1489974522533}, "extra_data": {}, "in_response_to": [{"text": "7", "occurrence": 2}]}}